opti_solve-0.1.1.dist-info/METADATA
opti_solve-0.1.1.dist-info/WHEEL
opti_solve/__init__.py
opti_solve/opti_solve.cp310-win_amd64.pyd
opti_solve-0.1.1.dist-info/RECORD
