Metadata-Version: 2.1
Name: opti_solve
Version: 0.1.1
Classifier: Programming Language :: Rust
Classifier: Programming Language :: Python :: Implementation :: CPython
Classifier: Programming Language :: Python :: Implementation :: PyPy
Summary: Common optimization algorithms
Keywords: opt,optimize
Author: HunLuanZhiZhu <zhuyihe@petalmail.com>
Author-email: HunLuanZhiZhu <zhuyihe@petalmail.com>
License: MIT OR Apache-2.0
Requires-Python: >=3.7
